jsonstraw/__init__.py
jsonstraw/straw.py
jsonstraw-0.1.3.dist-info/licenses/LICENSE
test/__init__.py
test/test_straw.py
jsonstraw-0.1.3.dist-info/METADATA
jsonstraw-0.1.3.dist-info/WHEEL
jsonstraw-0.1.3.dist-info/top_level.txt
jsonstraw-0.1.3.dist-info/RECORD
