Metadata-Version: 2.4
Name: jsonstraw
Version: 0.1.3
Author-email: Andrew Tarry <andrew.tarry@loqui-tech.com>
Project-URL: Homepage, https://github.com/Loqui-Tech/jsonstraw
Requires-Python: >=3.10
License-File: LICENSE
Requires-Dist: orjson<4,>=3.10
Dynamic: license-file
